pretres/main.py
pretres-1.0.0.dist-info/METADATA
pretres-1.0.0.dist-info/WHEEL
pretres-1.0.0.dist-info/entry_points.txt
pretres-1.0.0.dist-info/top_level.txt
pretres-1.0.0.dist-info/RECORD
