Metadata-Version: 2.4
Name: pretres
Version: 1.0.0
Summary: This game shows letters in a grid 4x4. All players write down as many words as they can find.
Author: Marko Klopčič
Classifier: Programming Language :: Python :: 3
Classifier: License :: OSI Approved :: GNU General Public License v2 (GPLv2)
Classifier: Operating System :: OS Independent
Requires-Python: >=3.12
Requires-Dist: pygame
